title_belt_nhl/__init__.py
title_belt_nhl/main.py
title_belt_nhl/models/nhl_team_schedule_response.py
title_belt_nhl/schedule.py
title_belt_nhl/service/nhl_api.py
title_belt_nhl/static/nhl_tms.py
title_belt_nhl/static/schedule_2023_2024.csv
title_belt_nhl/static/schedule_2024_2025.csv
title_belt_nhl/tests/test_files/mock_league_schedule.json
title_belt_nhl/tests/test_files/mock_league_schedule_big.json
title_belt_nhl/tests/test_schedule.py
title_belt_nhl/tests/test_utils.py
title_belt_nhl/utils.py
title_belt_nhl-0.3.6.dist-info/METADATA
title_belt_nhl-0.3.6.dist-info/WHEEL
title_belt_nhl-0.3.6.dist-info/entry_points.txt
title_belt_nhl-0.3.6.dist-info/RECORD
