Metadata-Version: 2.1
Name: title-belt-nhl
Version: 0.3.6
Summary: CLI tool to compute NHL Title Belt info.
Author: kawa2287
Requires-Python: >=3.10,<4.0
Classifier: Programming Language :: Python :: 3
Classifier: Programming Language :: Python :: 3.10
Classifier: Programming Language :: Python :: 3.11
Classifier: Programming Language :: Python :: 3.12
Classifier: Programming Language :: Python :: 3.13
Requires-Dist: click (>=8.1.7,<9.0.0)
Requires-Dist: requests (>=2.32.3,<3.0.0)
Requires-Dist: rich-click (>=1.8.3,<2.0.0)
